lstmAtten_datautils/__init__.py
lstmAtten_datautils/base_Conf.py
lstmAtten_datautils/data_loader.py
lstmAtten_datautils/process.py
tests/__init__.py
tests/test_datautils.py
lstmAtten_datautils-2.2.12.dist-info/LICENSE
lstmAtten_datautils-2.2.12.dist-info/METADATA
lstmAtten_datautils-2.2.12.dist-info/WHEEL
lstmAtten_datautils-2.2.12.dist-info/top_level.txt
lstmAtten_datautils-2.2.12.dist-info/RECORD
